{
  "rasa_nlu_data": {
    "common_examples": [
      {
        "intent": "greet",
        "text": "hey"
      },
      {
        "intent": "greet",
        "text": "howdy"
      },
      {
        "intent": "greet",
        "text": "hey there"
      },
      {
        "intent": "greet",
        "text": "hello"
      },
      {
        "intent": "greet",
        "text": "hi"
      },
      {
        "intent": "greet",
        "text": "dear sir"
      },
      {
        "intent": "greet",
        "text": "what's up"
      },
      {
        "intent": "greet",
        "text": "yo"
      }
    ],
    "regex_features": [],
    "entity_synonyms": []
  }
}